gh_pr_update_description.py
gh_pr_update_description-0.2.0.dist-info/METADATA
gh_pr_update_description-0.2.0.dist-info/WHEEL
gh_pr_update_description-0.2.0.dist-info/entry_points.txt
gh_pr_update_description-0.2.0.dist-info/top_level.txt
gh_pr_update_description-0.2.0.dist-info/RECORD
