Metadata-Version: 2.1
Name: gh-pr-update-description
Version: 0.2.0
Summary: Update Github PR description with top commit title + body
Home-page: https://github.com/noahp/gh-pr-update-description
Author: Noah Pendleton
Author-email: 2538614+noahp@users.noreply.github.com
License: UNKNOWN
Project-URL: Code, https://github.com/noahp/gh-pr-update-description
Project-URL: Issue tracker, https://github.com/noahp/gh-pr-update-description/issues
Platform: UNKNOWN
Classifier: License :: OSI Approved :: MIT License
Classifier: Programming Language :: Python :: 3.6
Classifier: Programming Language :: Python :: 3.7
Classifier: Programming Language :: Python :: 3.8
Classifier: Operating System :: OS Independent
Requires-Dist: click
Requires-Dist: gitpython
Requires-Dist: pygithub
